stock_computing_service/__init__.py
stock_computing_service/constants.py
stock_computing_service/database.py
stock_computing_service/extract/__init__.py
stock_computing_service/extract/api_wrapper.py
stock_computing_service/extract/extract.py
stock_computing_service/helpers.py
stock_computing_service/main.py
stock_computing_service/statistics/__init__.py
stock_computing_service/statistics/model.py
stock_computing_service/sync.py
stock_computing_service/transform/__init__.py
stock_computing_service/transform/transform.py
stock_computing_service-1.2.1a5.dist-info/METADATA
stock_computing_service-1.2.1a5.dist-info/WHEEL
stock_computing_service-1.2.1a5.dist-info/RECORD
