Metadata-Version: 2.1
Name: stock-computing-service
Version: 1.2.1a5
Summary: stock_computing_service
License: LICENSE
Keywords: stock,fastapi,ETL
Author: Shubham Raj
Author-email: shubhamraj2202@gmail.com
Requires-Python: >=3.9,<4.0
Classifier: License :: Other/Proprietary License
Classifier: Programming Language :: Python :: 3
Classifier: Programming Language :: Python :: 3.9
Classifier: Programming Language :: Python :: 3.10
Classifier: Programming Language :: Python :: 3.11
Requires-Dist: aiohttp (>=3.8.4,<4.0.0)
Requires-Dist: datamodel-code-generator (>=0.17.1,<0.18.0)
Requires-Dist: fastapi (>=0.92.0,<0.93.0)
Requires-Dist: gcloud (>=0.18.3,<0.19.0)
Requires-Dist: psycopg2-binary (>=2.9.5,<3.0.0)
Requires-Dist: pulumi (>=3.57.1,<4.0.0)
Requires-Dist: pulumi-gcp (>=6.51.0,<7.0.0)
Requires-Dist: pulumi-kubernetes (>=3.24.1,<4.0.0)
Requires-Dist: pulumi-random (>=4.12.0,<5.0.0)
Requires-Dist: pydantic
Requires-Dist: pytest (>=7.2.2,<8.0.0)
Requires-Dist: pytest-asyncio (>=0.21.0,<0.22.0)
Requires-Dist: python-dateutil (>=2.8.2,<3.0.0)
Requires-Dist: sqlalchemy (>=2.0.5.post1,<3.0.0)
Requires-Dist: uvicorn (>=0.20.0,<0.21.0)
